LICENSE
MANIFEST.in
README.md
setup.py
gsq/__init__.py
gsq/binary.py
gsq/ci_tests.py
gsq/discrete.py
gsq/gsq_testdata.py
gsq.egg-info/PKG-INFO
gsq.egg-info/SOURCES.txt
gsq.egg-info/dependency_links.txt
gsq.egg-info/requires.txt
gsq.egg-info/top_level.txt