Metadata-Version: 1.1
Name: gsq
Version: 0.1.6
Summary: G Square Conditional Independence Test
Home-page: https://github.com/keiichishima/gsq/
Author: Keiichi SHIMA
Author-email: keiichi@iijlab.net
License: GNU General Public License v2 or later (GPLv2+)
Platform: UNKNOWN
Classifier: Development Status :: 4 - Beta
Classifier: Environment :: Console
Classifier: Intended Audience :: Information Technology
Classifier: Intended Audience :: Science/Research
Classifier: License :: OSI Approved :: GNU General Public License v2 or later (GPLv2+)
Classifier: Programming Language :: Python :: 2.7
Classifier: Topic :: Scientific/Engineering :: Information Analysis
Classifier: Topic :: Software Development :: Libraries :: Python Modules
